upy_rabbitmq/__init__.py
upy_rabbitmq/base.py
upy_rabbitmq/callback.py
upy_rabbitmq/client.py
upy_rabbitmq/worker.py
upy_rabbitmq-0.0.6.dist-info/METADATA
upy_rabbitmq-0.0.6.dist-info/WHEEL
upy_rabbitmq-0.0.6.dist-info/top_level.txt
upy_rabbitmq-0.0.6.dist-info/RECORD
