Metadata-Version: 2.1
Name: upy-rabbitmq
Version: 0.0.6
Summary: Basic RabbitMQ
Home-page: https://github.com/UpyExplorer/upy-rabbitmq
Author: Fernando Celmer
Author-email: email@fernandocelmer.com
Classifier: Operating System :: OS Independent
Classifier: License :: OSI Approved :: MIT License
Classifier: Intended Audience :: Developers
Classifier: Natural Language :: English
Classifier: Programming Language :: Python :: 3.6
Classifier: Programming Language :: Python :: 3.7
Classifier: Programming Language :: Python :: 3.8
Classifier: Programming Language :: Python :: 3.9
Classifier: Programming Language :: Python :: 3.10
Classifier: Programming Language :: Python :: 3.11
Requires-Python: >=3.6
Requires-Dist: pika (==1.3.1)
Requires-Dist: python-dotenv (==1.0.0)
